OdooQtUi/__init__.py
OdooQtUi/connector.py
OdooQtUi/RPC/__init__.py
OdooQtUi/RPC/rpc.py
OdooQtUi/RPC/XmlRpc/__init__.py
OdooQtUi/RPC/XmlRpc/xmlRpc.py
OdooQtUi/images/Edit_Form.png
OdooQtUi/images/Login.png
OdooQtUi/images/Tree_with_search.png
OdooQtUi/images/lgplv3-147x51.png
OdooQtUi/interface/__init__.py
OdooQtUi/interface/login.py
OdooQtUi/interface/ui/__init__.py
OdooQtUi/interface/ui/compileAllui.py
OdooQtUi/interface/ui/ui_login.py
OdooQtUi/objects/__init__.py
OdooQtUi/objects/button.py
OdooQtUi/objects/fieldTemplate.py
OdooQtUi/objects/binary/__init__.py
OdooQtUi/objects/binary/binary.py
OdooQtUi/objects/boolean/__init__.py
OdooQtUi/objects/boolean/boolean.py
OdooQtUi/objects/char/__init__.py
OdooQtUi/objects/char/char.py
OdooQtUi/objects/date/__init__.py
OdooQtUi/objects/date/date.py
OdooQtUi/objects/datetimee/__init__.py
OdooQtUi/objects/datetimee/datetimee.py
OdooQtUi/objects/float/__init__.py
OdooQtUi/objects/float/float.py
OdooQtUi/objects/integer/__init__.py
OdooQtUi/objects/integer/integer.py
OdooQtUi/objects/many2many/__init__.py
OdooQtUi/objects/many2many/many2many.py
OdooQtUi/objects/many2one/__init__.py
OdooQtUi/objects/many2one/many2one.py
OdooQtUi/objects/one2many/__init__.py
OdooQtUi/objects/one2many/one2many.py
OdooQtUi/objects/selection/__init__.py
OdooQtUi/objects/selection/selection.py
OdooQtUi/objects/text/__init__.py
OdooQtUi/objects/text/text.py
OdooQtUi/utils_odoo_conn/__init__.py
OdooQtUi/utils_odoo_conn/constants.py
OdooQtUi/utils_odoo_conn/utils.py
OdooQtUi/utils_odoo_conn/utilsUi.py
OdooQtUi/views/__init__.py
OdooQtUi/views/form_obj.py
OdooQtUi/views/search_obj.py
OdooQtUi/views/templateView.py
OdooQtUi/views/tree_list_obj.py
OdooQtUi/views/tree_tree_obj.py
OdooQtUi/views/parser/__init__.py
OdooQtUi/views/parser/search_view.py
OdooQtUi/views/parser/search_view_old.py
OdooQtUi/views/parser/tree_list.py
OdooQtUi/views/parser/tree_tree.py
OdooQtUi-0.0.5.dist-info/.gitignore
OdooQtUi-0.0.5.dist-info/LICENSE
OdooQtUi-0.0.5.dist-info/METADATA
OdooQtUi-0.0.5.dist-info/WHEEL
OdooQtUi-0.0.5.dist-info/top_level.txt
OdooQtUi-0.0.5.dist-info/RECORD
