Metadata-Version: 2.1
Name: OdooQtUi
Version: 0.0.5
Summary: The project intend to get a fully qt ui version for odoo, providing form a search view to be used in non web environment, like Allocation extension.
Home-page: https://bitbucket.org/mboscolo/odoo_qt/
Author: Daniel Smerghetto
Author-email: daniel.smerghetto@omniasolutions.eu
License: UNKNOWN
Platform: UNKNOWN
Classifier: Programming Language :: Python :: 3
Classifier: License :: OSI Approved :: GNU Lesser General Public License v3 (LGPLv3)
Classifier: Operating System :: OS Independent
Requires-Dist: PySide2
